crystalai/__init__.py
crystalai/_crystalai_scripts.py
crystalai/api_requestor.py
crystalai/cli.py
crystalai/embeddings_utils.py
crystalai/error.py
crystalai/object_classes.py
crystalai/openai_object.py
crystalai/openai_response.py
crystalai/py.typed
crystalai/upload_progress.py
crystalai/util.py
crystalai/validators.py
crystalai/version.py
crystalai/wandb_logger.py
crystalai/api_resources/__init__.py
crystalai/api_resources/audio.py
crystalai/api_resources/chat_completion.py
crystalai/api_resources/completion.py
crystalai/api_resources/customer.py
crystalai/api_resources/deployment.py
crystalai/api_resources/edit.py
crystalai/api_resources/embedding.py
crystalai/api_resources/engine.py
crystalai/api_resources/error_object.py
crystalai/api_resources/file.py
crystalai/api_resources/fine_tune.py
crystalai/api_resources/fine_tuning.py
crystalai/api_resources/image.py
crystalai/api_resources/model.py
crystalai/api_resources/moderation.py
crystalai/api_resources/abstract/__init__.py
crystalai/api_resources/abstract/api_resource.py
crystalai/api_resources/abstract/createable_api_resource.py
crystalai/api_resources/abstract/deletable_api_resource.py
crystalai/api_resources/abstract/engine_api_resource.py
crystalai/api_resources/abstract/listable_api_resource.py
crystalai/api_resources/abstract/nested_resource_class_methods.py
crystalai/api_resources/abstract/paginatable_api_resource.py
crystalai/api_resources/abstract/updateable_api_resource.py
crystalai/api_resources/experimental/__init__.py
crystalai/api_resources/experimental/completion_config.py
crystalai/datalib/__init__.py
crystalai/datalib/common.py
crystalai/datalib/numpy_helper.py
crystalai/datalib/pandas_helper.py
crystalai/tests/__init__.py
crystalai/tests/test_api_requestor.py
crystalai/tests/test_endpoints.py
crystalai/tests/test_exceptions.py
crystalai/tests/test_file_cli.py
crystalai/tests/test_long_examples_validator.py
crystalai/tests/test_url_composition.py
crystalai/tests/test_util.py
crystalai-0.28.0.dist-info/LICENSE
crystalai-0.28.0.dist-info/METADATA
crystalai-0.28.0.dist-info/WHEEL
crystalai-0.28.0.dist-info/entry_points.txt
crystalai-0.28.0.dist-info/top_level.txt
crystalai-0.28.0.dist-info/zip-safe
crystalai-0.28.0.dist-info/RECORD
